isar_robot/__init__.py
isar_robot/inspections.py
isar_robot/robotinterface.py
isar_robot/simulation.py
isar_robot/telemetry.py
isar_robot/version.py
isar_robot/config/__init__.py
isar_robot/config/settings.env
isar_robot/config/settings.py
isar_robot/example_data/example_audio.wav
isar_robot/example_data/example_image.jpg
isar_robot/example_data/example_thermal_image.fff
isar_robot/example_data/example_thermal_video.mp4
isar_robot/example_data/example_video.mp4
isar_robot-1.5.21.dist-info/licenses/LICENSE
isar_robot-1.5.21.dist-info/METADATA
isar_robot-1.5.21.dist-info/WHEEL
isar_robot-1.5.21.dist-info/top_level.txt
isar_robot-1.5.21.dist-info/RECORD
